Workbook

Sheet Time Plan
A1: Product Launch Time Plan – Q4 2026
A2: Blue cells on yellow are inputs – change them and every date, total and the timeline update automatically.
A4: Key dates | D4: Lead times (days)
A5: Milestone | B5: Date | D5: Window | G5: Days
A6: Sourcing & PO | B6: 46315 | D6: Production / packing (PO → ship) | G6: =$B$7-$B$6 -> 8
A7: Ship (sea / air) | B7: 46323 | D7: Transit & customs (ship → launch) | G7: =$B$8-$B$7 -> 23
A8: Launch | B8: 46346 | D8: Total lead time (PO → launch) | G8: =$B$8-$B$6 -> 31
A9: Re-order | B9: 46366 | D9: Selling days (launch → re-order) | G9: =$B$9-$B$8 -> 20
A11: Products & purchase orders
A12: Product | B12: Order qty (units) | C12: Unit cost min (€) | D12: Unit cost max (€) | E12: PO value min (€) | F12: PO value max (€) | G12: Sourcing & PO | H12: Ship (sea / air) | I12: Launch | J12: Re-order | K12: Re-order stock arrives (est.) | L12: Units/day to sell out by re-order
A13: Pet Grooming Hammock Stand Iron | B13: 80 | C13: 5 | D13: 6 | E13: =B13*C13 -> 400 | F13: =B13*D13 -> 480 | G13: =$B$6 -> 46315 | H13: =$B$7 -> 46323 | I13: =$B$8 -> 46346 | J13: =$B$9 -> 46366 | K13: =J13+(I13-G13) -> 46397 | L13: =IF(J13>I13,B13/(J13-I13),0) -> 4
A14: Dog bark deterrent | B14: 70 | C14: 6 | D14: 7 | E14: =B14*C14 -> 420 | F14: =B14*D14 -> 490 | G14: =$B$6 -> 46315 | H14: =$B$7 -> 46323 | I14: =$B$8 -> 46346 | J14: =$B$9 -> 46366 | K14: =J14+(I14-G14) -> 46397 | L14: =IF(J14>I14,B14/(J14-I14),0) -> 3.5
A15: Toilet paper holder stand | B15: 50 | C15: 5 | D15: 6 | E15: =B15*C15 -> 250 | F15: =B15*D15 -> 300 | G15: =$B$6 -> 46315 | H15: =$B$7 -> 46323 | I15: =$B$8 -> 46346 | J15: =$B$9 -> 46366 | K15: =J15+(I15-G15) -> 46397 | L15: =IF(J15>I15,B15/(J15-I15),0) -> 2.5
A16: Free standing bird bath feeder | B16: 50 | C16: 5 | D16: 6 | E16: =B16*C16 -> 250 | F16: =B16*D16 -> 300 | G16: =$B$6 -> 46315 | H16: =$B$7 -> 46323 | I16: =$B$8 -> 46346 | J16: =$B$9 -> 46366 | K16: =J16+(I16-G16) -> 46397 | L16: =IF(J16>I16,B16/(J16-I16),0) -> 2.5
A17: Total | B17: =SUM(B13:B16) -> 250 | C17: =IF(B17>0,E17/B17,0) -> 5.28 | D17: =IF(B17>0,F17/B17,0) -> 6.28 | E17: =SUM(E13:E16) -> 1320 | F17: =SUM(F13:F16) -> 1570 | L17: =SUM(L13:L16) -> 12.5
A18: Quantities and unit cost ranges provided by you. Unit costs are product cost only – shipping, customs duty, VAT and marketplace fees are not included. Per-product dates follow the key dates above; overwrite a row's date if one product moves.
A20: Watch-outs
A21: 1. Only 8 days between PO (20 Oct) and shipping (28 Oct): confirm each supplier has stock ready, or production will push the ship date.
A22: 2. 23 days from ship to launch: realistic by air (about 5–10 days). Sea freight door-to-door usually takes 3–6 weeks, so sea risks missing the 20 Nov launch.
A23: 3. Black Friday (27 Nov) and Cyber Monday (30 Nov) fall in your first launch week – have listings and ads live before then.
A24: 4. A re-order on 10 Dec with the same ~31-day lead time arrives around 10 Jan, after Christmas. If sales start fast, bring the re-order forward.
A25: 5. Chinese New Year is 6 Feb 2027; factories close roughly late Jan to late Feb, so place any second re-order by early January.

Sheet Timeline
A1: Timeline (weekly)
A2: Dates come from the Key dates on the Time Plan tab. Only the Status column is edited here.
A4: Phase | B4: Start | C4: End | D4: Days | E4: Status | F4: ='Time Plan'!$B$6-WEEKDAY('Time Plan'!$B$6,3) -> 46314 | G4: =F4+7 -> 46321 | H4: =G4+7 -> 46328 | I4: =H4+7 -> 46335 | J4: =I4+7 -> 46342 | K4: =J4+7 -> 46349 | L4: =K4+7 -> 46356 | M4: =L4+7 -> 46363 | N4: =M4+7 -> 46370 | ... R4: =Q4+7 -> 46398
A5: Sourcing & PO placed | B5: ='Time Plan'!$B$6 -> 46315 | C5: ='Time Plan'!$B$6 -> 46315 | D5: =C5-B5+1 -> 1 | E5: Planned
A6: Production, QC & packing | B6: ='Time Plan'!$B$6+1 -> 46316 | C6: ='Time Plan'!$B$7-1 -> 46322 | D6: =C6-B6+1 -> 7 | E6: Planned
A7: Shipping (sea / air) & customs | B7: ='Time Plan'!$B$7 -> 46323 | C7: ='Time Plan'!$B$8-1 -> 46345 | D7: =C7-B7+1 -> 23 | E7: Planned
A8: Listings, photos & ads set-up | B8: ='Time Plan'!$B$7 -> 46323 | C8: ='Time Plan'!$B$8-1 -> 46345 | D8: =C8-B8+1 -> 23 | E8: Planned
A9: Launch | B9: ='Time Plan'!$B$8 -> 46346 | C9: ='Time Plan'!$B$8 -> 46346 | D9: =C9-B9+1 -> 1 | E9: Planned
A10: Black Friday → Cyber Monday | B10: =DATE(2026,11,27) -> 46353 | C10: =DATE(2026,11,30) -> 46356 | D10: =C10-B10+1 -> 4 | E10: Planned
A11: Selling period (launch → re-order) | B11: ='Time Plan'!$B$8 -> 46346 | C11: ='Time Plan'!$B$9 -> 46366 | D11: =C11-B11+1 -> 21 | E11: Planned
A12: Re-order PO placed | B12: ='Time Plan'!$B$9 -> 46366 | C12: ='Time Plan'!$B$9 -> 46366 | D12: =C12-B12+1 -> 1 | E12: Planned
A13: Re-order production & shipping (est.) | B13: ='Time Plan'!$B$9+1 -> 46367 | C13: ='Time Plan'!$B$9+('Time Plan'!$B$8-'Time Plan'!$B$6) -> 46397 | D13: =C13-B13+1 -> 31 | E13: Planned
A14: Blue bar = phase running that week · Orange = one-day milestone · Week columns start on Monday.

Sheet Products
A1: Product | B1: Market | C1: Local sellers | D1: Overseas sellers | E1: Fast (local stock) | F1: Listings | G1: Buyers / month | H1: Buyers per local seller | I1: Overseas share of sales % | J1: Typical price | K1: Currency | L1: Typical price (US$) | M1: Verdict
A2: toilet paper holder stand | B2: Australia | C2: 44 | D2: 0 | E2: 44 | F2: 44 | G2: 485.2 | H2: 11 | I2: 0 | J2: 29.99 | K2: A$ | L2: 19.35 | M2: 44 listings deliver fast. Crowded with local stock.
A3: toilet paper holder stand | B3: UAE | C3: 39 | D3: 2 | E3: 39 | F3: 43 | J3: 61.27 | K3: AED | L3: 16.68 | M3: 39 listings deliver fast. Crowded with local stock. 2 of 43 ship from overseas.
A4: free standing bird bath feeder | B4: Australia | C4: 41 | D4: 2 | E4: 40 | F4: 45 | G4: 207.9 | H4: 5.1 | I4: 0 | J4: 37.99 | K4: A$ | L4: 24.51 | M4: 40 listings deliver fast. Crowded with local stock. 2 of 45 ship from overseas.
A5: free standing bird bath feeder | B5: UAE | C5: 42 | D5: 5 | E5: 42 | F5: 47 | J5: 89.99 | K5: AED | L5: 24.5 | M5: 42 listings deliver fast. Crowded with local stock. 5 of 47 ship from overseas.
A6: dog bark deterrent | B6: Australia | C6: 39 | D6: 1 | E6: 39 | F6: 44 | G6: 1869.3 | H6: 47.9 | I6: 4 | J6: 32.99 | K6: A$ | L6: 21.28 | M6: 39 listings deliver fast. Crowded with local stock. 1 of 44 ship from overseas.
A7: dog bark deterrent | B7: UAE | C7: 34 | D7: 5 | E7: 34 | F7: 43 | G7: 69.3 | H7: 2 | I7: 0 | J7: 72.5 | K7: AED | L7: 19.74 | M7: 34 listings deliver fast. Crowded with local stock. 5 of 43 ship from overseas.
A8: Pet Grooming Hammock Stand Iron | B8: Australia | C8: 25 | D8: 22 | E8: 24 | F8: 47 | G8: 277.3 | H8: 11.1 | I8: 100 | J8: 39.99 | K8: A$ | L8: 25.8 | M8: 24 listings deliver fast. Crowded with local stock. 22 of 47 ship from overseas.
A9: Pet Grooming Hammock Stand Iron | B9: UAE | C9: 8 | D9: 40 | E9: 8 | F9: 48 | J9: 112.19 | K9: AED | L9: 30.55 | M9: 8 listings deliver fast. Some local competition. 40 of 48 ship from overseas.
